habitica/__init__.py
py_habitica-0.0.0.dist-info/LICENSE
py_habitica-0.0.0.dist-info/METADATA
py_habitica-0.0.0.dist-info/WHEEL
py_habitica-0.0.0.dist-info/top_level.txt
py_habitica-0.0.0.dist-info/RECORD
