Metadata-Version: 2.1
Name: py-habitica
Version: 0.0.0
Summary: An API wrapper for Habitica's API, in Python.
Home-page: https://github.com/ankitica/py-habitica
Author: skifli
License: MIT
Project-URL: Documentation, https://github.com/ankitica/py-habitica
Project-URL: Source, https://github.com/ankitica/py-habitica
Classifier: Development Status :: 2 - Pre-Alpha
Classifier: Intended Audience :: Developers
Classifier: License :: OSI Approved :: MIT License
Classifier: Natural Language :: English
Classifier: Operating System :: OS Independent
Classifier: Programming Language :: Python :: 3
License-File: LICENSE
